wherobots/__init__.py
wherobots/db/__init__.py
wherobots/db/connection.py
wherobots/db/constants.py
wherobots/db/cursor.py
wherobots/db/driver.py
wherobots/db/errors.py
wherobots/db/region.py
wherobots/db/runtime.py
wherobots/db/session_type.py
wherobots_python_dbapi-0.22.0.dist-info/METADATA
wherobots_python_dbapi-0.22.0.dist-info/WHEEL
wherobots_python_dbapi-0.22.0.dist-info/licenses/LICENSE
wherobots_python_dbapi-0.22.0.dist-info/RECORD
