Metadata-Version: 2.4
Name: wherobots-python-dbapi
Version: 0.22.0
Summary: Python DB-API driver for Wherobots DB
Project-URL: Homepage, https://github.com/wherobots/wherobots-python-dbapi-driver
Project-URL: Tracker, https://github.com/wherobots/wherobots-python-dbapi-driver/issues
Author-email: Maxime Petazzoni <max@wherobots.com>
License-Expression: Apache-2.0
License-File: LICENSE
Requires-Python: <4,>=3.8
Requires-Dist: cbor2>=5.6.3
Requires-Dist: packaging
Requires-Dist: pandas
Requires-Dist: pandas-stubs>=2.0.3.230814
Requires-Dist: pyarrow>=14.0.2
Requires-Dist: requests>=2.31.0
Requires-Dist: strenum<0.5,>=0.4.15
Requires-Dist: tenacity>=8.2.3
Requires-Dist: types-requests>=2.32.0.20241016
Requires-Dist: websockets>=13.0
Provides-Extra: test
Requires-Dist: pytest>=8.0.2; extra == 'test'
